aws_key_rotate/__init__.py
aws_key_rotate/__main__.py
aws_key_rotate/cli.py
aws_key_rotate-0.1.2.dist-info/METADATA
aws_key_rotate-0.1.2.dist-info/WHEEL
aws_key_rotate-0.1.2.dist-info/entry_points.txt
aws_key_rotate-0.1.2.dist-info/top_level.txt
aws_key_rotate-0.1.2.dist-info/RECORD
