Metadata-Version: 2.4
Name: aws_key_rotate
Version: 0.1.2
Summary: Rotate your AWS access keys and update your credentials file.
Requires-Python: >=3.11
Requires-Dist: boto3
